pyPhyNR/__init__.py
pyPhyNR/matlab_to_python_nr_gen.py
pyPhyNR/core/__init__.py
pyPhyNR/core/carrier.py
pyPhyNR/core/channel_types.py
pyPhyNR/core/definitions.py
pyPhyNR/core/modulation.py
pyPhyNR/core/numerology.py
pyPhyNR/core/re_mapping.py
pyPhyNR/core/resources.py
pyPhyNR/core/signal_builder.py
pyPhyNR/core/waveform.py
pyPhyNR/core/channels/__init__.py
pyPhyNR/core/channels/base.py
pyPhyNR/core/channels/coreset.py
pyPhyNR/core/channels/dmrs.py
pyPhyNR/core/channels/pbch.py
pyPhyNR/core/channels/pdcch.py
pyPhyNR/core/channels/pdsch.py
pyPhyNR/core/channels/pss.py
pyPhyNR/core/channels/ssblock.py
pyPhyNR/core/channels/sss.py
pyPhyNR/utils/__init__.py
pyPhyNR/utils/plotting.py
pyPhyNR/waveforms/__init__.py
pyPhyNR/waveforms/ofdm.py
pyphynr-0.1.0.dist-info/licenses/LICENSE
pyphynr-0.1.0.dist-info/METADATA
pyphynr-0.1.0.dist-info/WHEEL
pyphynr-0.1.0.dist-info/top_level.txt
pyphynr-0.1.0.dist-info/RECORD
